<?xml version="1.0"?>
<EmbeddedProjectSample xmlns:xsi="http://www.w3.org/2001/XMLSchema-instance" xmlns:xsd="http://www.w3.org/2001/XMLSchema">
	  <Name>IoT icmp</Name>
	  <Description>This sample demonstrates a IoT ICMP.</Description>
	  <DoNotUpgradeCToCpp>true</DoNotUpgradeCToCpp>
  <RequiredFrameworks>
	<string>com.sysprogs.arm.nordic.nrf5x.util</string>
	<string>com.sysprogs.arm.nordic.nrf5x.periph</string>
	<string>com.sysprogs.arm.nordic.nrf5x.boards</string>
    <string>com.sysprogs.arm.nordic.nrf5x.libraries</string>
    <string>com.sysprogs.arm.nordic.nrf5x.ble_common</string>
    <string>com.sysprogs.arm.nordic.nrfx.ble_advertising</string>
    <string>com.sysprogs.arm.nordic.nrf5x.iot</string>
  </RequiredFrameworks>
  <ConditionalErrors>
	<ConditionalError>
		<ErrorCondition xsi:type="Not">
			<Argument xsi:type="MatchesRegex">
				<Expression>$$com.sysprogs.bspoptions.nrf5x.softdevice$$</Expression>
				<Regex>s.*</Regex>
				<IgnoreCase>false</IgnoreCase>
			</Argument>
		</ErrorCondition>
		<ErrorText>Please select a BLE Peripheral-capable softdevice on the previous page.</ErrorText>
	</ConditionalError>
  </ConditionalErrors>
  <DefaultConfiguration>
    <Entries>
	   <KeyValue>
		<Key>com.sysprogs.bspoptions.nrf5x.iot.tls_instance</Key>
        <Value></Value>
      </KeyValue>

      <KeyValue>
        <Key>com.sysprogs.bspoptions.nrf5x.board.type</Key>
        <Value>PCA10040</Value>
      </KeyValue>
      <KeyValue>
        <Key>com.sysprogs.bspoptions.nrf5x.board.bsp_mode</Key>
        <Value />
      </KeyValue>
      <KeyValue>
        <Key>com.sysprogs.bspoptions.nrf5x.board.bsp_uart</Key>
        <Value>BSP_UART_SUPPORT</Value>
      </KeyValue>
      <KeyValue>
        <Key>com.sysprogs.bspoptions.nrf5x.libraries.button</Key>
        <Value>yes</Value>
      </KeyValue>
      <KeyValue>
        <Key>com.sysprogs.bspoptions.nrf5x.libraries.crc16</Key>
        <Value>yes</Value>
      </KeyValue>
      <KeyValue>
        <Key>com.sysprogs.bspoptions.nrf5x.libraries.fifo</Key>
        <Value>yes</Value>
      </KeyValue>
      
      <KeyValue>
        <Key>com.sysprogs.bspoptions.nrf5x.libraries.scheduler</Key>
        <Value>normal</Value>
      </KeyValue>    
      <KeyValue>
        <Key>com.sysprogs.bspoptions.nrf5x.libraries.sha256</Key>
        <Value>yes</Value>
      </KeyValue>
     
      <KeyValue>
        <Key>com.sysprogs.bspoptions.nrf5x.libraries.timer</Key>
        <Value>appsh</Value>
      </KeyValue>
      <KeyValue>
        <Key>com.sysprogs.bspoptions.nrf5x.libraries.trace</Key>
        <Value>yes</Value>
      </KeyValue>
      <KeyValue>
        <Key>com.sysprogs.bspoptions.nrf5x.libraries.uart</Key>
        <Value>yes</Value>
      </KeyValue>
      <KeyValue>
        <Key>com.sysprogs.bspoptions.nrf5x.libraries.util</Key>
        <Value>yes</Value>
      </KeyValue>
	  
      <KeyValue>
        <Key>com.sysprogs.bspoptions.nrf5x.iot.ble_ipsp</Key>
        <Value>yes</Value>
      </KeyValue>
      <KeyValue>
        <Key>com.sysprogs.bspoptions.nrf5x.iot.ipv6_stack</Key>
        <Value>yes</Value>
      </KeyValue>
      <KeyValue>
        <Key>com.sysprogs.bspoptions.nrf5x.iot.iot_timer</Key>
        <Value>yes</Value>
      </KeyValue>
     <KeyValue>
        <Key>com.sysprogs.bspoptions.nrf5x.iot.ble_6lowpan</Key>
        <Value>yes</Value>
      </KeyValue>
     <KeyValue>
        <Key>com.sysprogs.bspoptions.nrf5x.iot.medium</Key>
        <Value>yes</Value>
      </KeyValue>
       <KeyValue>
        <Key>com.sysprogs.bspoptions.nrf5x.libraries.mem_manager</Key>
        <Value>yes</Value>
      </KeyValue>
  	  <KeyValue>
        <Key>com.sysprogs.bspoptions.nrf5x.uart_driver</Key>
        <Value>yes</Value>
      </KeyValue>

    </Entries>
	</DefaultConfiguration>
</EmbeddedProjectSample>